{
  "total_requests": 30,
  "total_response_time": 16.62334370613098,
  "endpoint_metrics": {
    "GET main.analyze_database": {
      "count": 5,
      "total_time": 14.923612117767334,
      "avg_time": 2.9847224235534666,
      "min_time": 0.0004951953887939453,
      "max_time": 6.048209190368652,
      "status_codes": {
        "302": 2,
        "200": 3
      }
    },
    "GET main.login": {
      "count": 2,
      "total_time": 0.1734318733215332,
      "avg_time": 0.0867159366607666,
      "min_time": 0.0014553070068359375,
      "max_time": 0.17197656631469727,
      "status_codes": {
        "200": 2
      }
    },
    "GET static": {
      "count": 20,
      "total_time": 0.21240878105163574,
      "avg_time": 0.010620439052581787,
      "min_time": 0.0002155303955078125,
      "max_time": 0.17055392265319824,
      "status_codes": {
        "200": 6,
        "304": 14
      }
    },
    "POST main.login": {
      "count": 1,
      "total_time": 0.4502556324005127,
      "avg_time": 0.4502556324005127,
      "min_time": 0.4502556324005127,
      "max_time": 0.4502556324005127,
      "status_codes": {
        "302": 1
      }
    },
    "GET main.index": {
      "count": 1,
      "total_time": 0.1473238468170166,
      "avg_time": 0.1473238468170166,
      "min_time": 0.1473238468170166,
      "max_time": 0.1473238468170166,
      "status_codes": {
        "200": 1
      }
    },
    "GET main.databases": {
      "count": 1,
      "total_time": 0.7163114547729492,
      "avg_time": 0.7163114547729492,
      "min_time": 0.7163114547729492,
      "max_time": 0.7163114547729492,
      "status_codes": {
        "200": 1
      }
    }
  },
  "slow_requests": [
    {
      "timestamp": "2025-09-17T17:42:56.816405",
      "endpoint": "GET main.analyze_database",
      "response_time": 6.048209190368652,
      "status_code": 200
    }
  ],
  "alerts": [
    {
      "timestamp": "2025-09-17T17:42:56.817610",
      "message": "Endpoint GET main.analyze_database is responding slowly (>5s)",
      "severity": "warning"
    }
  ]
}