{
  "total_requests": 53,
  "total_response_time": 2.24704909324646,
  "endpoint_metrics": {
    "GET main.admin_roles": {
      "count": 8,
      "total_time": 0.3627588748931885,
      "avg_time": 0.04534485936164856,
      "min_time": 0.0005538463592529297,
      "max_time": 0.16443204879760742,
      "status_codes": {
        "302": 1,
        "200": 7
      }
    },
    "GET main.login": {
      "count": 1,
      "total_time": 0.46553754806518555,
      "avg_time": 0.46553754806518555,
      "min_time": 0.46553754806518555,
      "max_time": 0.46553754806518555,
      "status_codes": {
        "200": 1
      }
    },
    "POST main.login": {
      "count": 1,
      "total_time": 0.2806587219238281,
      "avg_time": 0.2806587219238281,
      "min_time": 0.2806587219238281,
      "max_time": 0.2806587219238281,
      "status_codes": {
        "302": 1
      }
    },
    "GET main.index": {
      "count": 1,
      "total_time": 0.11456108093261719,
      "avg_time": 0.11456108093261719,
      "min_time": 0.11456108093261719,
      "max_time": 0.11456108093261719,
      "status_codes": {
        "200": 1
      }
    },
    "GET static": {
      "count": 35,
      "total_time": 0.1428842544555664,
      "avg_time": 0.00408240727015904,
      "min_time": 0.0003960132598876953,
      "max_time": 0.0947718620300293,
      "status_codes": {
        "304": 33,
        "200": 2
      }
    },
    "GET main.admin": {
      "count": 6,
      "total_time": 0.8481080532073975,
      "avg_time": 0.1413513422012329,
      "min_time": 0.006195068359375,
      "max_time": 0.6154477596282959,
      "status_codes": {
        "200": 6
      }
    },
    "GET main.create_role": {
      "count": 1,
      "total_time": 0.03254055976867676,
      "avg_time": 0.03254055976867676,
      "min_time": 0.03254055976867676,
      "max_time": 0.03254055976867676,
      "status_codes": {
        "200": 1
      }
    }
  },
  "slow_requests": [],
  "alerts": []
}